setup.py
sa_flask_restful_resource/__init__.py
sa_flask_restful_resource.egg-info/PKG-INFO
sa_flask_restful_resource.egg-info/SOURCES.txt
sa_flask_restful_resource.egg-info/dependency_links.txt
sa_flask_restful_resource.egg-info/requires.txt
sa_flask_restful_resource.egg-info/top_level.txt