Metadata-Version: 1.0
Name: sa-flask-restful-resource
Version: 0.0.3
Summary: base class for sqlalchemy and flask-restless
Home-page: UNKNOWN
Author: UNKNOWN
Author-email: UNKNOWN
License: UNKNOWN
Platform: UNKNOWN
